BuzhouShanzhiduBoCsapp/README.md
BuzhouShanzhiduBoCsapp/__init__.py
BuzhouShanzhiduBoCsapp/__main__.py
BuzhouShanzhiduBoCsapp/file.epub
BuzhouShanzhiduBoCsapp/index.html
BuzhouShanzhiduBoCsapp/css/__init__.py
BuzhouShanzhiduBoCsapp/css/annotations.css
BuzhouShanzhiduBoCsapp/css/main.css
BuzhouShanzhiduBoCsapp/css/normalize.css
BuzhouShanzhiduBoCsapp/css/popup.css
BuzhouShanzhiduBoCsapp/font/__init__.py
BuzhouShanzhiduBoCsapp/font/fontello.eot
BuzhouShanzhiduBoCsapp/font/fontello.svg
BuzhouShanzhiduBoCsapp/font/fontello.ttf
BuzhouShanzhiduBoCsapp/font/fontello.woff
BuzhouShanzhiduBoCsapp/img/__init__.py
BuzhouShanzhiduBoCsapp/img/annotator-glyph-sprite.png
BuzhouShanzhiduBoCsapp/img/annotator-icon-sprite.png
BuzhouShanzhiduBoCsapp/img/apple-touch-icon.png
BuzhouShanzhiduBoCsapp/img/cancelfullscreen.png
BuzhouShanzhiduBoCsapp/img/close.png
BuzhouShanzhiduBoCsapp/img/fullscreen.png
BuzhouShanzhiduBoCsapp/img/loader.gif
BuzhouShanzhiduBoCsapp/img/menu-icon.png
BuzhouShanzhiduBoCsapp/img/save.png
BuzhouShanzhiduBoCsapp/img/saved.png
BuzhouShanzhiduBoCsapp/img/settings-s.png
BuzhouShanzhiduBoCsapp/img/settings.png
BuzhouShanzhiduBoCsapp/img/star.png
BuzhouShanzhiduBoCsapp/js/__init__.py
BuzhouShanzhiduBoCsapp/js/epub.js
BuzhouShanzhiduBoCsapp/js/epub.min.js
BuzhouShanzhiduBoCsapp/js/epub.min.map
BuzhouShanzhiduBoCsapp/js/hooks.min.js
BuzhouShanzhiduBoCsapp/js/hooks.min.map
BuzhouShanzhiduBoCsapp/js/reader.js
BuzhouShanzhiduBoCsapp/js/reader.js.map
BuzhouShanzhiduBoCsapp/js/reader.min.js
BuzhouShanzhiduBoCsapp/js/reader.min.map
BuzhouShanzhiduBoCsapp/js/hooks/__init__.py
BuzhouShanzhiduBoCsapp/js/hooks/extensions/__init__.py
BuzhouShanzhiduBoCsapp/js/hooks/extensions/highlight.js
BuzhouShanzhiduBoCsapp/js/libs/__init__.py
BuzhouShanzhiduBoCsapp/js/libs/jquery.min.js
BuzhouShanzhiduBoCsapp/js/libs/localforage.min.js
BuzhouShanzhiduBoCsapp/js/libs/screenfull.js
BuzhouShanzhiduBoCsapp/js/libs/screenfull.min.js
BuzhouShanzhiduBoCsapp/js/libs/zip.min.js
buzhou_shanzhidu_bo_csapp-2024.3.2.0.dist-info/METADATA
buzhou_shanzhidu_bo_csapp-2024.3.2.0.dist-info/WHEEL
buzhou_shanzhidu_bo_csapp-2024.3.2.0.dist-info/entry_points.txt
buzhou_shanzhidu_bo_csapp-2024.3.2.0.dist-info/top_level.txt
buzhou_shanzhidu_bo_csapp-2024.3.2.0.dist-info/RECORD
